{
  "kind": "collectionType",
  "collectionName": "blog_posts",
  "info": {
    "singularName": "blog-post",
    "pluralName": "blog-posts",
    "displayName": "Blog_Post"
  },
  "options": {
    "draftAndPublish": true
  },
  "pluginOptions": {
    "i18n": {
      "localized": true
    }
  },
  "attributes": {
    "Title": {
      "type": "string",
      "pluginOptions": {
        "i18n": {
          "localized": true
        }
      },
      "required": true,
      "unique": true
    },
    "Slug": {
      "type": "uid",
      "targetField": "Title"
    },
    "Summary": {
      "type": "blocks",
      "pluginOptions": {
        "i18n": {
          "localized": true
        }
      },
      "required": true
    },
    "Content": {
      "type": "blocks",
      "pluginOptions": {
        "i18n": {
          "localized": true
        }
      },
      "required": true
    },
    "Featured_Image": {
      "type": "media",
      "pluginOptions": {
        "i18n": {
          "localized": true
        }
      },
      "multiple": false,
      "allowedTypes": [
        "images",
        "files",
        "videos",
        "audios"
      ]
    }
  }
}
